token2audio/__init__.py
token2audio/app.py
token2audio/download.py
token2audio/protocol.py
token2audio/server.py
token2audio/assets/female.wav
token2audio/assets/index.html
token2audio/assets/male.wav
token2audio/cosyvoice2/__init__.py
token2audio/cosyvoice2/flow/__init__.py
token2audio/cosyvoice2/flow/decoder_dit.py
token2audio/cosyvoice2/flow/flow.py
token2audio/cosyvoice2/flow/flow_matching.py
token2audio/cosyvoice2/transformer/__init__.py
token2audio/cosyvoice2/transformer/attention.py
token2audio/cosyvoice2/transformer/embedding.py
token2audio/cosyvoice2/transformer/encoder_layer.py
token2audio/cosyvoice2/transformer/positionwise_feed_forward.py
token2audio/cosyvoice2/transformer/subsampling.py
token2audio/cosyvoice2/transformer/upsample_encoder_v2.py
token2audio/cosyvoice2/utils/__init__.py
token2audio/cosyvoice2/utils/class_utils.py
token2audio/cosyvoice2/utils/common.py
token2audio/cosyvoice2/utils/mask.py
token2audio/flashcosyvoice/__init__.py
token2audio/flashcosyvoice/flashcosyvoice/__init__.py
token2audio/flashcosyvoice/flashcosyvoice/cli.py
token2audio/flashcosyvoice/flashcosyvoice/config.py
token2audio/flashcosyvoice/flashcosyvoice/cosyvoice2.py
token2audio/flashcosyvoice/flashcosyvoice/cosyvoice3.py
token2audio/flashcosyvoice/flashcosyvoice/engine/__init__.py
token2audio/flashcosyvoice/flashcosyvoice/engine/block_manager.py
token2audio/flashcosyvoice/flashcosyvoice/engine/llm_engine.py
token2audio/flashcosyvoice/flashcosyvoice/engine/model_runner.py
token2audio/flashcosyvoice/flashcosyvoice/engine/scheduler.py
token2audio/flashcosyvoice/flashcosyvoice/engine/sequence.py
token2audio/flashcosyvoice/flashcosyvoice/modules/__init__.py
token2audio/flashcosyvoice/flashcosyvoice/modules/flow.py
token2audio/flashcosyvoice/flashcosyvoice/modules/hifigan.py
token2audio/flashcosyvoice/flashcosyvoice/modules/qwen2.py
token2audio/flashcosyvoice/flashcosyvoice/modules/sampler.py
token2audio/flashcosyvoice/flashcosyvoice/modules/flow_components/__init__.py
token2audio-0.1.10.dist-info/METADATA
token2audio-0.1.10.dist-info/WHEEL
token2audio-0.1.10.dist-info/entry_points.txt
token2audio-0.1.10.dist-info/top_level.txt
token2audio-0.1.10.dist-info/RECORD
