Metadata-Version: 2.4
Name: token2audio
Version: 0.1.10
Summary: Token2Audio Server Package
Requires-Python: >=3.8
Requires-Dist: fastapi
Requires-Dist: uvicorn[standard]
Requires-Dist: torch
Requires-Dist: torchaudio
Requires-Dist: numpy
Requires-Dist: s3tokenizer
Requires-Dist: onnxruntime
Requires-Dist: librosa
Requires-Dist: scipy
Requires-Dist: psutil
Requires-Dist: hyperpyyaml
Requires-Dist: huggingface_hub
Requires-Dist: transformers
Requires-Dist: diffusers
Provides-Extra: gpu
Requires-Dist: triton>=3.0.0; extra == "gpu"
Requires-Dist: flash-attn; extra == "gpu"
Requires-Dist: nvidia-ml-py; extra == "gpu"
Dynamic: description
Dynamic: description-content-type
Dynamic: provides-extra
Dynamic: requires-dist
Dynamic: requires-python
Dynamic: summary
